README.txt
setup.py
test/test.py
webassets_libsass/__init__.py
webassets_libsass.egg-info/PKG-INFO
webassets_libsass.egg-info/SOURCES.txt
webassets_libsass.egg-info/dependency_links.txt
webassets_libsass.egg-info/requires.txt
webassets_libsass.egg-info/top_level.txt