Metadata-Version: 1.1
Name: webassets-libsass
Version: 0.2
Summary: Filter for asset management "webassets" that uses "libsass"
Home-page: https://bitbucket.org/jhuss/webassets-libsass
Author: Jesús Jerez
Author-email: jerezmoreno@gmail.com
License: BSD
Platform: UNKNOWN
Classifier: License :: OSI Approved :: BSD License
Classifier: Environment :: Web Environment
Classifier: Operating System :: OS Independent
Classifier: Programming Language :: Python
Classifier: Programming Language :: Python :: 3
Classifier: Topic :: Software Development :: Libraries
